{
    "callsign": "NOZ601  ",
    "endTime": "2024/06/04-09:59:56",
    "icao24": "4aca0b",
    "path": [
        [
            1717502904,
            60.4324,
            9.9998,
            3962,
            86,
            false
        ],
        [
            1717503701,
            60.435,
            10.0803,
            3962,
            86,
            false
        ],
        [
            1717503736,
            60.4357,
            10.099,
            3657,
            86,
            false
        ],
        [
            1717503753,
            60.4349,
            10.0773,
            3962,
            86,
            false
        ],
        [
            1717504573,
            60.4381,
            10.1649,
            3657,
            85,
            false
        ],
        [
            1717505211,
            60.4396,
            10.2073,
            3657,
            86,
            false
        ],
        [
            1717505223,
            60.4401,
            10.2242,
            3352,
            86,
            false
        ],
        [
            1717505233,
            60.4397,
            10.2115,
            3657,
            86,
            false
        ],
        [
            1717505242,
            60.4401,
            10.2242,
            3352,
            86,
            false
        ],
        [
            1717505270,
            60.4396,
            10.2085,
            3657,
            86,
            false
        ],
        [
            1717505996,
            60.4424,
            10.2965,
            3352,
            85,
            false
        ]
    ],
    "startTime": "2024/06/04-09:08:24",
    "baro_altitude": 3771.9,
    "category": 0,
    "geo_altitude": 3733.8,
    "keys": [
        "icao24",
        "firstSeen",
        "estDepartureAirport",
        "lastSeen",
        "estArrivalAirport",
        "callsign",
        "estDepartureAirportHorizDistance",
        "estDepartureAirportVertDistance",
        "estArrivalAirportHorizDistance",
        "estArrivalAirportVertDistance",
        "departureAirportCandidatesCount",
        "arrivalAirportCandidatesCount"
    ],
    "last_contact": 1717504573,
    "latitude": 60.4381,
    "longitude": 10.1649,
    "on_ground": false,
    "origin_country": "Sweden",
    "position_source": 0,
    "sensors": null,
    "spi": false,
    "squawk": "2545",
    "time_position": 1717504573,
    "true_track": 85.63,
    "velocity": 168.71,
    "vertical_rate": -6.83,
    "arrivalAirportCandidatesCount": 0,
    "departureAirportCandidatesCount": 0,
    "estArrivalAirport": null,
    "estArrivalAirportHorizDistance": null,
    "estArrivalAirportVertDistance": null,
    "estDepartureAirport": null,
    "estDepartureAirportHorizDistance": null,
    "estDepartureAirportVertDistance": null,
    "firstSeen": 1717502904,
    "lastSeen": 1717505996
}