{
    "callsign": "TAP860  ",
    "endTime": "2024/06/04-08:23:41",
    "icao24": "4952c4",
    "path": [
        [
            1717499425,
            41.3053,
            0.3413,
            11277,
            89,
            false
        ],
        [
            1717499425,
            41.3053,
            0.3413,
            11277,
            89,
            false
        ],
        [
            1717499463,
            41.3093,
            1.0588,
            11582,
            89,
            false
        ],
        [
            1717499489,
            41.3053,
            0.3468,
            11277,
            89,
            false
        ],
        [
            1717499496,
            41.3092,
            1.0504,
            11582,
            89,
            false
        ],
        [
            1717499545,
            41.3093,
            1.0616,
            11277,
            89,
            false
        ],
        [
            1717499602,
            41.3093,
            1.0742,
            11582,
            89,
            false
        ],
        [
            1717499690,
            41.3054,
            0.3612,
            11277,
            89,
            false
        ],
        [
            1717499703,
            41.3094,
            1.0909,
            11582,
            89,
            false
        ],
        [
            1717499715,
            41.3055,
            0.3647,
            11277,
            89,
            false
        ],
        [
            1717499853,
            41.3094,
            1.1081,
            11582,
            89,
            false
        ],
        [
            1717499853,
            41.3094,
            1.1081,
            11277,
            89,
            false
        ],
        [
            1717499864,
            41.3094,
            1.1133,
            11582,
            89,
            false
        ],
        [
            1717499876,
            41.3055,
            0.3743,
            11277,
            89,
            false
        ],
        [
            1717500017,
            41.3094,
            1.1326,
            11582,
            90,
            false
        ],
        [
            1717500033,
            41.3094,
            1.1204,
            11277,
            89,
            false
        ],
        [
            1717500172,
            41.3094,
            1.1449,
            11582,
            90,
            false
        ],
        [
            1717500172,
            41.3094,
            1.1449,
            11277,
            89,
            false
        ],
        [
            1717500210,
            41.3094,
            1.1464,
            11582,
            90,
            false
        ],
        [
            1717500210,
            41.3094,
            1.1464,
            11277,
            89,
            false
        ],
        [
            1717500221,
            41.3094,
            1.1507,
            11582,
            90,
            false
        ]
    ],
    "startTime": "2024/06/04-08:10:25",
    "baro_altitude": 11582.4,
    "category": 0,
    "geo_altitude": 11917.68,
    "keys": [
        "icao24",
        "firstSeen",
        "estDepartureAirport",
        "lastSeen",
        "estArrivalAirport",
        "callsign",
        "estDepartureAirportHorizDistance",
        "estDepartureAirportVertDistance",
        "estArrivalAirportHorizDistance",
        "estArrivalAirportVertDistance",
        "departureAirportCandidatesCount",
        "arrivalAirportCandidatesCount"
    ],
    "last_contact": 1717500036,
    "latitude": 41.3094,
    "longitude": 1.1254,
    "on_ground": false,
    "origin_country": "Portugal",
    "position_source": 0,
    "sensors": null,
    "spi": false,
    "squawk": "1031",
    "time_position": 1717500036,
    "true_track": 89.87,
    "velocity": 232.01,
    "vertical_rate": 0,
    "arrivalAirportCandidatesCount": 0,
    "departureAirportCandidatesCount": 0,
    "estArrivalAirport": null,
    "estArrivalAirportHorizDistance": null,
    "estArrivalAirportVertDistance": null,
    "estDepartureAirport": null,
    "estDepartureAirportHorizDistance": null,
    "estDepartureAirportVertDistance": null,
    "firstSeen": 1717499425,
    "lastSeen": 1717500221
}