{
    "callsign": "N650DR  ",
    "endTime": "2024/06/14-18:13:19",
    "icao24": "a88d15",
    "path": [
        [
            1718397686,
            38.0192,
            -84.6246,
            304,
            221,
            false
        ],
        [
            1718397711,
            38.0023,
            -84.6431,
            609,
            220,
            false
        ],
        [
            1718397748,
            37.9966,
            -84.6492,
            914,
            216,
            false
        ],
        [
            1718397786,
            37.9355,
            -84.6193,
            1828,
            103,
            false
        ],
        [
            1718397800,
            37.9316,
            -84.5963,
            1828,
            102,
            false
        ],
        [
            1718397823,
            37.925,
            -84.5581,
            2133,
            102,
            false
        ],
        [
            1718397847,
            37.918,
            -84.5188,
            2438,
            103,
            false
        ],
        [
            1718397885,
            37.9053,
            -84.4517,
            2743,
            103,
            false
        ],
        [
            1718397930,
            37.888,
            -84.3634,
            3048,
            103,
            false
        ],
        [
            1718397978,
            37.8684,
            -84.2651,
            3352,
            104,
            false
        ],
        [
            1718398026,
            37.8479,
            -84.1638,
            3657,
            104,
            false
        ],
        [
            1718398072,
            37.8276,
            -84.0639,
            3962,
            104,
            false
        ],
        [
            1718398106,
            37.8124,
            -83.9898,
            4267,
            104,
            false
        ],
        [
            1718398127,
            37.8032,
            -83.945,
            4572,
            104,
            false
        ],
        [
            1718398171,
            37.7831,
            -83.8471,
            4876,
            104,
            false
        ],
        [
            1718398204,
            37.7687,
            -83.7779,
            5181,
            104,
            false
        ],
        [
            1718398237,
            37.7535,
            -83.705,
            5486,
            104,
            false
        ],
        [
            1718398274,
            37.7363,
            -83.6231,
            5791,
            104,
            false
        ],
        [
            1718398304,
            37.7224,
            -83.5566,
            6096,
            104,
            false
        ],
        [
            1718398343,
            37.7045,
            -83.4708,
            6400,
            104,
            false
        ],
        [
            1718398393,
            37.681,
            -83.3591,
            6705,
            104,
            false
        ],
        [
            1718398821,
            37.4469,
            -82.2801,
            7010,
            106,
            false
        ],
        [
            1718398821,
            37.4469,
            -82.2801,
            7010,
            114,
            false
        ],
        [
            1718399596,
            36.9927,
            -80.4554,
            4267,
            114,
            false
        ],
        [
            1718399599,
            36.9903,
            -80.4486,
            3962,
            114,
            false
        ]
    ],
    "startTime": "2024/06/14-17:41:26",
    "baro_altitude": 7010.4,
    "category": 0,
    "geo_altitude": 7277.1,
    "keys": [
        "icao24",
        "firstSeen",
        "estDepartureAirport",
        "lastSeen",
        "estArrivalAirport",
        "callsign",
        "estDepartureAirportHorizDistance",
        "estDepartureAirportVertDistance",
        "estArrivalAirportHorizDistance",
        "estArrivalAirportVertDistance",
        "departureAirportCandidatesCount",
        "arrivalAirportCandidatesCount"
    ],
    "last_contact": 1718399392,
    "latitude": 37.4469,
    "longitude": -82.2801,
    "on_ground": false,
    "origin_country": "United States",
    "position_source": 0,
    "sensors": null,
    "spi": false,
    "squawk": null,
    "time_position": 1718398821,
    "true_track": 106.47,
    "velocity": 223.17,
    "vertical_rate": -10.4,
    "arrivalAirportCandidatesCount": 0,
    "departureAirportCandidatesCount": 272,
    "estArrivalAirport": null,
    "estArrivalAirportHorizDistance": null,
    "estArrivalAirportVertDistance": null,
    "estDepartureAirport": "KLEX",
    "estDepartureAirportHorizDistance": 2237,
    "estDepartureAirportVertDistance": 265,
    "firstSeen": 1718397686,
    "lastSeen": 1718399599
}