{
    "callsign": "N316TG  ",
    "endTime": "2024/06/14-13:20:56",
    "icao24": "a35ecb",
    "path": [
        [
            1718380043,
            34.4629,
            -84.5059,
            609,
            246,
            false
        ],
        [
            1718380049,
            34.4617,
            -84.5094,
            609,
            247,
            false
        ],
        [
            1718380144,
            34.4436,
            -84.5582,
            914,
            245,
            false
        ],
        [
            1718380227,
            34.4271,
            -84.6007,
            1219,
            244,
            false
        ],
        [
            1718380325,
            34.4069,
            -84.6527,
            1524,
            244,
            false
        ],
        [
            1718380393,
            34.3929,
            -84.6886,
            1828,
            245,
            false
        ],
        [
            1718380487,
            34.3693,
            -84.7494,
            2133,
            244,
            false
        ],
        [
            1718380546,
            34.3532,
            -84.7907,
            2438,
            245,
            false
        ],
        [
            1718380615,
            34.3339,
            -84.8401,
            2743,
            244,
            false
        ],
        [
            1718380683,
            34.3149,
            -84.8886,
            3048,
            244,
            false
        ],
        [
            1718380755,
            34.2941,
            -84.9414,
            3352,
            244,
            false
        ],
        [
            1718381646,
            33.9347,
            -85.8459,
            3657,
            244,
            false
        ],
        [
            1718381848,
            33.8503,
            -86.0544,
            3657,
            244,
            false
        ],
        [
            1718381901,
            33.8278,
            -86.1098,
            3352,
            243,
            false
        ],
        [
            1718381944,
            33.8089,
            -86.1562,
            3048,
            244,
            false
        ],
        [
            1718382010,
            33.7862,
            -86.2119,
            2743,
            243,
            false
        ],
        [
            1718382056,
            33.7599,
            -86.276,
            2438,
            243,
            false
        ]
    ],
    "startTime": "2024/06/14-12:47:23",
    "baro_altitude": 3787.14,
    "category": 0,
    "geo_altitude": 3977.64,
    "keys": [
        "icao24",
        "firstSeen",
        "estDepartureAirport",
        "lastSeen",
        "estArrivalAirport",
        "callsign",
        "estDepartureAirportHorizDistance",
        "estDepartureAirportVertDistance",
        "estArrivalAirportHorizDistance",
        "estArrivalAirportVertDistance",
        "departureAirportCandidatesCount",
        "arrivalAirportCandidatesCount"
    ],
    "last_contact": 1718380973,
    "latitude": 34.2129,
    "longitude": -85.1488,
    "on_ground": false,
    "origin_country": "United States",
    "position_source": 0,
    "sensors": null,
    "spi": false,
    "squawk": null,
    "time_position": 1718380973,
    "true_track": 244.54,
    "velocity": 107.69,
    "vertical_rate": 0,
    "arrivalAirportCandidatesCount": 0,
    "departureAirportCandidatesCount": 327,
    "estArrivalAirport": null,
    "estArrivalAirportHorizDistance": null,
    "estArrivalAirportVertDistance": null,
    "estDepartureAirport": "KJZP",
    "estDepartureAirportHorizDistance": 4089,
    "estDepartureAirportVertDistance": 400,
    "firstSeen": 1718380043,
    "lastSeen": 1718382056
}